ansi_to_html_py-0.1.0.dist-info/METADATA
ansi_to_html_py-0.1.0.dist-info/WHEEL
ansi_to_html_py-0.1.0.dist-info/licenses/LICENSE
ansi_to_html/__init__.py
ansi_to_html/ansi_to_html.pypy311-pp73-x86-linux-gnu.so
ansi_to_html_py-0.1.0.dist-info/RECORD
