Metadata-Version: 2.4
Name: ansi-to-html-py
Version: 0.1.0
Classifier: Intended Audience :: Developers
Classifier: License :: OSI Approved :: MIT License
Classifier: Programming Language :: Rust
Classifier: Programming Language :: Python :: Implementation :: CPython
Classifier: Programming Language :: Python :: Implementation :: PyPy
Classifier: Operating System :: OS Independent
Classifier: Programming Language :: Python :: 3
Classifier: Programming Language :: Python :: 3.10
Classifier: Programming Language :: Python :: 3.11
Classifier: Programming Language :: Python :: 3.12
Classifier: Programming Language :: Python :: 3.13
Classifier: Programming Language :: Python :: 3.9
Requires-Dist: maturin[patchelf]>=1.8.2 ; extra == 'dev'
Requires-Dist: pdm>=2.22.3 ; extra == 'dev'
Requires-Dist: pdm-bump>=0.9.10 ; extra == 'dev'
Requires-Dist: pre-commit>=4.1.0 ; extra == 'dev'
Requires-Dist: markdown>=3.7 ; extra == 'bench'
Requires-Dist: markdown2>=2.5.3 ; extra == 'bench'
Provides-Extra: dev
Provides-Extra: bench
License-File: LICENSE
Summary: Python bindings for the ansi-to-html Rust library, a fast ANSI terminal output to HTML converter
Keywords: ansi,html,rust
Author-email: Louis Maddox <louismmx@gmail.com>
Requires-Python: >=3.9
Project-URL: Homepage, https://github.com/lmmx/ansi-to-html
Project-URL: Repository, https://github.com/lmmx/ansi-to-html.git
